<Properties StartupConfiguration="{8979BDCF-CC5A-4EA5-87A4-F6273E382989}|">
  <MonoDevelop.Ide.Workbench>
    <Pads>
      <Pad Id="ProjectPad">
        <State name="__root__">
          <Node name="TCDF_APL_WEB_SINJ" expanded="True">
            <Node name="TCDF.Sinj.Web" expanded="True">
              <Node name="References" expanded="True" />
              <Node name="ashx" expanded="True">
                <Node name="Autocomplete" expanded="True">
                  <Node name="TipoDeNormaAutocomplete.ashx" expanded="True">
                    <Node name="TipoDeNormaAutocomplete.ashx.cs" selected="True" />
                  </Node>
                </Node>
              </Node>
              <Node name="PesquisarNorma.aspx" expanded="True" />
            </Node>
          </Node>
        </State>
      </Pad>
    </Pads>
  </MonoDevelop.Ide.Workbench>
  <MonoDevelop.Ide.DebuggingService.PinnedWatches />
  <DisabledProjects>
    <String>../../../../../../Desktop/20181212.1/Projetos/neo.BRLightRest/neo.BRLightREST.csproj</String>
    <String>../../Projetos/TCDF.Sinj/TCDF.Sinj.csproj</String>
  </DisabledProjects>
  <MonoDevelop.Ide.ItemProperties.TCDF.Sinj.Web PreferredExecutionTarget="/usr/bin/google-chrome-stable" />
  <MonoDevelop.Ide.Workspace ActiveConfiguration="Release" />
  <MonoDevelop.Ide.DebuggingService.Breakpoints>
    <BreakpointStore>
      <Breakpoint file="/home/brlight/Data/DEV_HOST/_SINJ/sinj/Projetos/TCDF.Sinj/RN/HistoricoDePesquisaRN.cs" line="13" column="1" />
      <Breakpoint file="/home/brlight/Data/DEV_HOST/_SINJ/sinj/Projetos/TCDF.Sinj/RN/TipoDeNormaRN.cs" line="42" column="29" />
      <Breakpoint file="/home/brlight/Data/DEV_HOST/_SINJ/sinj/Projetos/TCDF.Sinj/AD/TipoDeNormaAD.cs" line="50" column="25" />
      <Breakpoint file="/home/brlight/Data/DEV_HOST/_SINJ/sinj/Projetos/TCDF.Sinj/AD/TipoDeNormaAD.cs" line="10" column="1" />
      <Breakpoint file="/home/brlight/Data/DEV_HOST/_SINJ/sinj/Projetos/TCDF.Sinj/OV/TipoDeNormaOV.cs" line="7" column="18" />
    </BreakpointStore>
  </MonoDevelop.Ide.DebuggingService.Breakpoints>
  <MultiItemStartupConfigurations />
</Properties>