<Properties StartupConfiguration="{8979BDCF-CC5A-4EA5-87A4-F6273E382989}|">
  <MonoDevelop.Ide.Workbench ActiveDocument="../../Projetos/TCDF.Sinj/RN/NormaRN.cs">
    <Files>
      <File FileName="TCDF.Sinj.Web/ashx/Datatable/ResultadoDePesquisaNormaDatatable.ashx.cs" Line="90" Column="22" />
      <File FileName="TCDF.Sinj.Web/Sinj.Master" Line="184" Column="35" />
      <File FileName="TCDF.Sinj.Web/ashx/Exclusao/VideExcluir.ashx.cs" Line="103" Column="41" />
      <File FileName="../../Projetos/TCDF.Sinj/RN/NormaRN.cs" Line="1349" Column="94" />
    </Files>
    <Pads>
      <Pad Id="ProjectPad">
        <State name="__root__">
          <Node name="TCDF_APL_WEB_SINJ" expanded="True">
            <Node name="TCDF.Sinj.Web" expanded="True">
              <Node name="References" selected="True" />
            </Node>
          </Node>
        </State>
      </Pad>
    </Pads>
  </MonoDevelop.Ide.Workbench>
  <MonoDevelop.Ide.DebuggingService.PinnedWatches />
  <DisabledProjects>
    <String>../../Projetos/TCDF.Sinj/TCDF.Sinj.csproj</String>
  </DisabledProjects>
  <MonoDevelop.Ide.ItemProperties.TCDF.Sinj.Web PreferredExecutionTarget="/usr/bin/google-chrome-stable" />
  <MonoDevelop.Ide.Workspace ActiveConfiguration="Release" />
  <MonoDevelop.Ide.DebuggingService.Breakpoints>
    <BreakpointStore>
      <Breakpoint enabled="false" file="/home/brlight/Data/DEV_HOST/_SINJ/sinj/Projetos/TCDF.Sinj/RN/NormaRN.cs" line="1879" column="41" />
      <Breakpoint enabled="false" file="/home/brlight/Data/DEV_HOST/_SINJ/sinj/Projetos/TCDF.Sinj/RN/NormaRN.cs" line="1951" column="24" />
      <Breakpoint enabled="false" file="/home/brlight/Data/DEV_HOST/_SINJ/sinj/Projetos/TCDF.Sinj/RN/NormaRN.cs" line="1350" column="68" />
    </BreakpointStore>
  </MonoDevelop.Ide.DebuggingService.Breakpoints>
  <MultiItemStartupConfigurations />
</Properties>